nbtemplater/__init__.py
nbtemplater/cli.py
nbtemplater/functions.py
nbtemplater/line_status.py
nbtemplater-0.1.2.dist-info/LICENSE
nbtemplater-0.1.2.dist-info/METADATA
nbtemplater-0.1.2.dist-info/WHEEL
nbtemplater-0.1.2.dist-info/entry_points.txt
nbtemplater-0.1.2.dist-info/top_level.txt
nbtemplater-0.1.2.dist-info/RECORD
