Metadata-Version: 2.1
Name: nbtemplater
Version: 0.1.2
Summary: A tool to split a template Jupyter notebook into a solution and a task version.
Home-page: https://github.com/sebastian-steiner/nbtemplater
Author: Sebastian Steiner
Author-email: sebastian.steiner@tuta.io
License: MIT
Keywords: Notebooks,Grading,Homework,Teaching
Platform: UNKNOWN
Classifier: Programming Language :: Python
Classifier: Programming Language :: Python :: 3
Classifier: Programming Language :: Python :: 3.5
Classifier: Programming Language :: Python :: 3.6
Requires-Python: >=3.5
Requires-Dist: Click
Requires-Dist: colorama
